automount_log_collator/Collator.py
automount_log_collator/Config.py
automount_log_collator/KeyedReader.py
automount_log_collator/KeyedReaderTree.py
automount_log_collator/Merger.py
automount_log_collator/Scanner.py
automount_log_collator/__init__.py
automount_log_collator/__main__.py
automount_log_collator/test_util.py
automount_log_collator/util.py
automount_log_collator/version.py
automount_log_collator-0.1.0.dist-info/LICENSE
automount_log_collator-0.1.0.dist-info/METADATA
automount_log_collator-0.1.0.dist-info/WHEEL
automount_log_collator-0.1.0.dist-info/entry_points.txt
automount_log_collator-0.1.0.dist-info/top_level.txt
automount_log_collator-0.1.0.dist-info/RECORD
